setup.py
whtmacro/__init__.py
whtmacro/__main__.py
whtmacro/livesyntax.py
whtmacro/searchTree.py
whtmacro/syntaxengine.py
whtmacro.egg-info/PKG-INFO
whtmacro.egg-info/SOURCES.txt
whtmacro.egg-info/dependency_links.txt
whtmacro.egg-info/entry_points.txt
whtmacro.egg-info/top_level.txt