Metadata-Version: 1.0
Name: whtmacro
Version: 0.3.1
Summary: help create document use HTML template
Home-page: https://github.com/fiathux/whtmacro
Author: Fiathux Su
Author-email: fiathux@gmail.com
License: GPLv2
Keywords: documention
Platform: any
